freeze_dried_data/__init__.py
freeze_dried_data/efficient_index.py
freeze_dried_data/freeze_dried_data.py
freeze_dried_data/freeze_dried_data_old.py
freeze_dried_data/test_efficient_index.py
freeze_dried_data/test_freeze_dried_data.py
freeze_dried_data/test_freeze_dried_data_old.py
freeze_dried_data-2.6.4.dist-info/licenses/LICENSE
freeze_dried_data-2.6.4.dist-info/METADATA
freeze_dried_data-2.6.4.dist-info/WHEEL
freeze_dried_data-2.6.4.dist-info/top_level.txt
freeze_dried_data-2.6.4.dist-info/RECORD
